<?xml version="1.0" encoding="UTF-8" ?><annotation><source><origin>GF2/GF3</origin><filename>171.tif</filename></source><objects><object><centerpoint>771.500000, 203.500000</centerpoint><description>None</description><type>rectangle</type><keypoints><keypoint>768.000000, 192.000000</keypoint><keypoint>757.000000, 198.000000</keypoint><keypoint>785.000000, 200.000000</keypoint><keypoint>771.000000, 213.000000</keypoint></keypoints><points><point>757.483684, 212.026974</point><point>756.483694, 183.026985</point><point>784.483685, 185.026704</point><point>785.483674, 214.026693</point><point>757.483684, 212.026974</point></points><coordinate>pixel</coordinate><possibleresult><name>Boeing737</name><probability>0.9997351765632629</probability></possibleresult></object><object><centerpoint>739.000000, 199.750000</centerpoint><description>None</description><type>rectangle</type><keypoints><keypoint>749.000000, 195.000000</keypoint><keypoint>725.000000, 198.000000</keypoint><keypoint>740.000000, 209.000000</keypoint><keypoint>736.000000, 185.000000</keypoint></keypoints><points><point>725.519457, 212.612879</point><point>720.519475, 183.612925</point><point>748.519429, 176.612659</point><point>753.519411, 205.612613</point><point>725.519457, 212.612879</point></points><coordinate>pixel</coordinate><possibleresult><name>Boeing737</name><probability>0.999716579914093</probability></possibleresult></object><object><centerpoint>729.000000, 226.000000</centerpoint><description>None</description><type>rectangle</type><keypoints><keypoint>729.000000, 216.000000</keypoint><keypoint>716.000000, 224.000000</keypoint><keypoint>744.000000, 230.000000</keypoint><keypoint>723.000000, 239.000000</keypoint></keypoints><points><point>709.146147, 235.171157</point><point>721.146204, 208.171053</point><point>750.146320, 216.170792</point><point>738.146263, 243.170897</point><point>709.146147, 235.171157</point></points><coordinate>pixel</coordinate><possibleresult><name>Boeing737</name><probability>0.9996284246444702</probability></possibleresult></object><object><description>None</description><type>rectangle</type><keypoints><keypoint>164.000000, 432.000000</keypoint><keypoint>173.000000, 434.000000</keypoint><keypoint>153.000000, 437.000000</keypoint><keypoint>165.000000, 446.000000</keypoint></keypoints><points><point>154.499626, 446.998525</point><point>149.499648, 426.998571</point><point>170.499598, 422.998373</point><point>175.499577, 442.998327</point><point>154.499626, 446.998525</point></points><coordinate>pixel</coordinate><possibleresult><name>Boeing737</name><probability>0.9996243715286255</probability></possibleresult></object><object><centerpoint>617.000000, 271.500000</centerpoint><description>None</description><type>rectangle</type><keypoints><keypoint>609.000000, 266.000000</keypoint><keypoint>622.000000, 266.000000</keypoint><keypoint>623.000000, 279.000000</keypoint><keypoint>607.000000, 283.000000</keypoint></keypoints><points><point>599.002814, 274.497005</point><point>615.002894, 257.496930</point><point>631.002974, 274.496845</point><point>615.002894, 291.496920</point><point>599.002814, 274.497005</point></points><coordinate>pixel</coordinate><possibleresult><name>Boeing737</name><probability>0.9996175765991211</probability></possibleresult></object><object><centerpoint>602.000000, 59.000000</centerpoint><description>None</description><type>rectangle</type><keypoints><keypoint>598.000000, 52.000000</keypoint><keypoint>607.000000, 56.000000</keypoint><keypoint>595.000000, 63.000000</keypoint></keypoints><points><point>597.997945, 69.495558</point><point>591.997973, 56.495597</point><point>603.997934, 47.495513</point><point>609.997906, 60.495474</point><point>597.997945, 69.495558</point></points><coordinate>pixel</coordinate><possibleresult><name>Boeing737</name><probability>0.9992948770523071</probability></possibleresult></object><object><centerpoint>927.666667, 144.666667</centerpoint><description>None</description><type>rectangle</type><keypoints><keypoint>932.000000, 138.000000</keypoint><keypoint>914.000000, 140.000000</keypoint><keypoint>938.000000, 151.000000</keypoint></keypoints><points><point>923.448972, 149.951407</point><point>902.449221, 129.951635</point><point>930.448903, 131.951331</point><point>951.448653, 151.951103</point><point>923.448972, 149.951407</point></points><coordinate>pixel</coordinate><possibleresult><name>Boeing737</name><probability>0.9992421865463257</probability></possibleresult></object><object><centerpoint>211.000000, 431.000000</centerpoint><description>None</description><type>rectangle</type><keypoints><keypoint>217.000000, 424.000000</keypoint><keypoint>202.000000, 425.000000</keypoint><keypoint>219.000000, 437.000000</keypoint><keypoint>206.000000, 438.000000</keypoint></keypoints><points><point>194.480995, 431.984643</point><point>208.481080, 416.984563</point><point>225.481179, 428.984456</point><point>211.481095, 443.984537</point><point>194.480995, 431.984643</point></points><coordinate>pixel</coordinate><possibleresult><name>Boeing737</name><probability>0.9991186261177063</probability></possibleresult></object><object><centerpoint>915.000000, 162.000000</centerpoint><description>None</description><type>rectangle</type><keypoints><keypoint>916.000000, 159.000000</keypoint><keypoint>903.000000, 161.000000</keypoint><keypoint>930.000000, 165.000000</keypoint><keypoint>912.000000, 170.000000</keypoint></keypoints><points><point>890.011153, 167.993491</point><point>914.011462, 153.993317</point><point>942.011815, 159.993111</point><point>918.011507, 173.993285</point><point>890.011153, 167.993491</point></points><coordinate>pixel</coordinate><possibleresult><name>Boeing737</name><probability>0.998421311378479</probability></possibleresult></object></objects><research><author>UFMS</author><provider>UFMS</provider><pluginclass>Detection</pluginclass><pluginname>Airplane Detection and Recognition</pluginname><version>4.0</version><time>2020-07-2020-11</time></research></annotation>