<?xml version="1.0" encoding="UTF-8" ?><annotation><source><origin>GF2/GF3</origin><filename>25.tif</filename></source><objects><object><centerpoint>990.000000, 198.500000</centerpoint><description>None</description><type>rectangle</type><keypoints><keypoint>982.000000, 180.000000</keypoint><keypoint>1005.000000, 208.000000</keypoint><keypoint>975.000000, 209.000000</keypoint><keypoint>1006.500000, 183.500000</keypoint></keypoints><points><point>989.503594, 223.987052</point><point>959.503758, 192.987212</point><point>992.503588, 164.987035</point><point>1022.503423, 195.986875</point><point>989.503594, 223.987052</point></points><coordinate>pixel</coordinate><possibleresult><name>A330</name><probability>0.999987006187439</probability></possibleresult></object><object><centerpoint>185.000000, 912.000000</centerpoint><description>None</description><type>rectangle</type><keypoints><keypoint>201.000000, 881.000000</keypoint><keypoint>151.000000, 922.000000</keypoint><keypoint>204.000000, 935.000000</keypoint><keypoint>161.500000, 884.000000</keypoint></keypoints><points><point>175.749761, 959.779150</point><point>124.750022, 902.779431</point><point>181.749741, 852.779116</point><point>232.749479, 909.778835</point><point>175.749761, 959.779150</point></points><coordinate>pixel</coordinate><possibleresult><name>Boeing787</name><probability>0.9998509883880615</probability></possibleresult></object><object><centerpoint>1011.000000, 883.750000</centerpoint><description>None</description><type>rectangle</type><keypoints><keypoint>1018.000000, 865.000000</keypoint><keypoint>1002.000000, 872.000000</keypoint><keypoint>1019.000000, 889.000000</keypoint><keypoint>1001.000000, 894.000000</keypoint></keypoints><points><point>1008.625656, 908.298115</point><point>992.625709, 878.298195</point><point>1011.625658, 849.298098</point><point>1027.625605, 879.298018</point><point>1008.625656, 908.298115</point></points><coordinate>pixel</coordinate><possibleresult><name>Boeing737</name><probability>0.9996581077575684</probability></possibleresult></object><object><centerpoint>973.000000, 504.000000</centerpoint><description>None</description><type>rectangle</type><keypoints><keypoint>956.000000, 493.000000</keypoint><keypoint>985.000000, 495.000000</keypoint><keypoint>954.000000, 517.000000</keypoint></keypoints><points><point>967.483548, 530.001997</point><point>939.483721, 503.002154</point><point>970.483540, 481.001980</point><point>998.483367, 508.001823</point><point>967.483548, 530.001997</point></points><coordinate>pixel</coordinate><possibleresult><name>A330</name><probability>0.9995275735855103</probability></possibleresult></object><object><centerpoint>1008.000000, 555.000000</centerpoint><description>None</description><type>rectangle</type><keypoints><keypoint>993.000000, 543.000000</keypoint><keypoint>1018.000000, 547.000000</keypoint><keypoint>990.000000, 570.000000</keypoint></keypoints><points><point>997.995526, 583.993297</point><point>977.995623, 553.993426</point><point>1007.995492, 531.993230</point><point>1027.995395, 561.993100</point><point>997.995526, 583.993297</point></points><coordinate>pixel</coordinate><possibleresult><name>Boeing737</name><probability>0.9994839429855347</probability></possibleresult></object><object><centerpoint>580.750000, 455.750000</centerpoint><description>None</description><type>rectangle</type><keypoints><keypoint>574.000000, 440.000000</keypoint><keypoint>597.000000, 442.000000</keypoint><keypoint>594.000000, 464.000000</keypoint><keypoint>567.000000, 467.000000</keypoint></keypoints><points><point>577.997431, 481.996271</point><point>555.997535, 449.996408</point><point>585.997406, 425.996219</point><point>607.997302, 457.996083</point><point>577.997431, 481.996271</point></points><coordinate>pixel</coordinate><possibleresult><name>A330</name><probability>0.9994813799858093</probability></possibleresult></object><object><centerpoint>951.000000, 44.500000</centerpoint><description>None</description><type>rectangle</type><keypoints><keypoint>943.000000, 25.000000</keypoint><keypoint>966.000000, 25.000000</keypoint><keypoint>939.000000, 53.000000</keypoint><keypoint>965.000000, 55.000000</keypoint></keypoints><points><point>950.503541, 68.004933</point><point>927.503644, 36.005063</point><point>955.503530, 9.004904</point><point>978.503426, 41.004774</point><point>950.503541, 68.004933</point></points><coordinate>pixel</coordinate><possibleresult><name>Boeing737</name><probability>0.9992994070053101</probability></possibleresult></object><object><centerpoint>114.000000, 960.500000</centerpoint><description>None</description><type>rectangle</type><keypoints><keypoint>94.000000, 941.000000</keypoint><keypoint>125.000000, 943.000000</keypoint><keypoint>93.000000, 967.000000</keypoint><keypoint>127.000000, 979.000000</keypoint></keypoints><points><point>108.725164, 996.766109</point><point>75.725323, 957.766285</point><point>111.725160, 922.766093</point><point>144.725002, 961.765917</point><point>108.725164, 996.766109</point></points><coordinate>pixel</coordinate><possibleresult><name>other</name><probability>0.9986734390258789</probability></possibleresult></object><object><centerpoint>324.000000, 799.750000</centerpoint><description>None</description><type>rectangle</type><keypoints><keypoint>333.000000, 788.000000</keypoint><keypoint>311.000000, 806.000000</keypoint><keypoint>336.000000, 813.000000</keypoint><keypoint>310.500000, 785.000000</keypoint></keypoints><points><point>295.001148, 801.498165</point><point>317.001241, 766.498034</point><point>347.001362, 795.497842</point><point>325.001270, 830.497972</point><point>295.001148, 801.498165</point></points><coordinate>pixel</coordinate><possibleresult><name>Boeing737</name><probability>0.9981189370155334</probability></possibleresult></object><object><centerpoint>615.000000, 497.500000</centerpoint><description>None</description><type>rectangle</type><keypoints><keypoint>609.000000, 483.000000</keypoint><keypoint>632.000000, 483.000000</keypoint><keypoint>631.000000, 507.000000</keypoint><keypoint>600.000000, 511.000000</keypoint></keypoints><points><point>584.003332, 496.997080</point><point>616.003520, 468.996924</point><point>648.003708, 496.996760</point><point>616.003520, 524.996916</point><point>584.003332, 496.997080</point></points><coordinate>pixel</coordinate><possibleresult><name>A330</name><probability>0.9963659048080444</probability></possibleresult></object><object><centerpoint>296.000000, 562.500000</centerpoint><description>None</description><type>rectangle</type><keypoints><keypoint>289.000000, 547.000000</keypoint><keypoint>309.000000, 571.000000</keypoint><keypoint>282.000000, 572.000000</keypoint><keypoint>314.000000, 547.500000</keypoint></keypoints><points><point>264.501719, 559.998537</point><point>297.501940, 531.998358</point><point>332.502172, 555.998161</point><point>299.501952, 583.998340</point><point>264.501719, 559.998537</point></points><coordinate>pixel</coordinate><possibleresult><name>Boeing737</name><probability>0.818679928779602</probability></possibleresult></object><object><centerpoint>784.000000, 460.000000</centerpoint><description>None</description><type>rectangle</type><keypoints><keypoint>775.000000, 449.000000</keypoint><keypoint>802.000000, 453.000000</keypoint><keypoint>775.000000, 474.000000</keypoint><keypoint>803.000000, 474.000000</keypoint></keypoints><points><point>786.788653, 486.277967</point><point>759.788817, 460.278115</point><point>790.788639, 437.277944</point><point>817.788475, 463.277796</point><point>786.788653, 486.277967</point></points><coordinate>pixel</coordinate><possibleresult><name>A330</name><probability>0.6073218584060669</probability></possibleresult></object></objects><research><author>UFMS</author><provider>UFMS</provider><pluginclass>Detection</pluginclass><pluginname>Airplane Detection and Recognition</pluginname><version>4.0</version><time>2020-07-2020-11</time></research></annotation>