<?xml version="1.0" encoding="UTF-8" ?><annotation><source><origin>GF2/GF3</origin><filename>309.tif</filename></source><objects><object><centerpoint>108.500000, 448.000000</centerpoint><description>None</description><type>rectangle</type><keypoints><keypoint>93.000000, 422.000000</keypoint><keypoint>57.000000, 443.000000</keypoint><keypoint>151.000000, 443.000000</keypoint><keypoint>103.000000, 469.000000</keypoint></keypoints><points><point>88.492480, 484.999735</point><point>18.493144, 416.000380</point><point>115.492237, 407.999486</point><point>185.491572, 476.998841</point><point>88.492480, 484.999735</point></points><coordinate>pixel</coordinate><possibleresult><name>other</name><probability>0.9999769926071167</probability></possibleresult></object><object><centerpoint>124.500000, 560.500000</centerpoint><description>None</description><type>rectangle</type><keypoints><keypoint>99.000000, 529.000000</keypoint><keypoint>168.000000, 558.000000</keypoint><keypoint>115.000000, 594.000000</keypoint><keypoint>66.500000, 567.000000</keypoint></keypoints><points><point>91.955433, 615.940584</point><point>25.955894, 527.941185</point><point>134.955149, 513.940192</point><point>200.954688, 601.939591</point><point>91.955433, 615.940584</point></points><coordinate>pixel</coordinate><possibleresult><name>Boeing737</name><probability>0.9949107766151428</probability></possibleresult></object><object><description>None</description><type>rectangle</type><keypoints><keypoint>65.000000, 267.000000</keypoint><keypoint>127.000000, 297.000000</keypoint><keypoint>26.000000, 302.500000</keypoint><keypoint>85.500000, 322.500000</keypoint></keypoints><points><point>49.320725, 348.975749</point><point>-10.678881, 259.976320</point><point>97.320426, 251.975292</point><point>157.320032, 340.974721</point><point>49.320725, 348.975749</point></points><coordinate>pixel</coordinate><possibleresult><name>Boeing737</name><probability>0.9925922155380249</probability></possibleresult></object></objects><research><author>UFMS</author><provider>UFMS</provider><pluginclass>Detection</pluginclass><pluginname>Airplane Detection and Recognition</pluginname><version>4.0</version><time>2020-07-2020-11</time></research></annotation>