<?xml version="1.0" encoding="UTF-8" ?><annotation><source><origin>GF2/GF3</origin><filename>337.tif</filename></source><objects><object><centerpoint>367.166667, 821.500000</centerpoint><description>None</description><type>rectangle</type><keypoints><keypoint>385.000000, 800.000000</keypoint><keypoint>346.000000, 819.000000</keypoint><keypoint>371.000000, 847.000000</keypoint><keypoint>404.000000, 827.500000</keypoint></keypoints><points><point>330.501637, 846.496982</point><point>361.501800, 789.496700</point><point>424.502113, 800.496123</point><point>393.501950, 857.496405</point><point>330.501637, 846.496982</point></points><coordinate>pixel</coordinate><possibleresult><name>A330</name><probability>0.9989224672317505</probability></possibleresult></object><object><centerpoint>571.500000, 781.500000</centerpoint><description>None</description><type>rectangle</type><keypoints><keypoint>567.000000, 762.000000</keypoint><keypoint>605.000000, 789.000000</keypoint><keypoint>540.000000, 795.000000</keypoint><keypoint>585.000000, 813.000000</keypoint></keypoints><points><point>547.863107, 825.961003</point><point>531.863157, 762.961159</point><point>596.862995, 756.960525</point><point>612.862946, 819.960369</point><point>547.863107, 825.961003</point></points><coordinate>pixel</coordinate><possibleresult><name>Boeing777</name><probability>0.9955260157585144</probability></possibleresult></object><object><centerpoint>727.833333, 424.500000</centerpoint><description>None</description><type>rectangle</type><keypoints><keypoint>699.000000, 384.000000</keypoint><keypoint>781.000000, 423.000000</keypoint><keypoint>716.000000, 469.000000</keypoint><keypoint>660.500000, 430.500000</keypoint></keypoints><points><point>679.496865, 488.993399</point><point>624.497128, 372.993933</point><point>753.496534, 364.992680</point><point>808.496271, 480.992147</point><point>679.496865, 488.993399</point></points><coordinate>pixel</coordinate><possibleresult><name>ARJ21</name><probability>0.9924423694610596</probability></possibleresult></object></objects><research><author>UFMS</author><provider>UFMS</provider><pluginclass>Detection</pluginclass><pluginname>Airplane Detection and Recognition</pluginname><version>4.0</version><time>2020-07-2020-11</time></research></annotation>