<?xml version="1.0" encoding="UTF-8" ?><annotation><source><origin>GF2/GF3</origin><filename>14.tif</filename></source><objects><object><centerpoint>998.000000, 975.000000</centerpoint><description>None</description><type>rectangle</type><keypoints><keypoint>993.000000, 933.000000</keypoint><keypoint>1020.000000, 961.000000</keypoint><keypoint>969.000000, 992.000000</keypoint><keypoint>1018.000000, 993.000000</keypoint></keypoints><points><point>977.497899, 1029.491507</point><point>958.497949, 952.491667</point><point>1025.497807, 911.491090</point><point>1044.497757, 988.490931</point><point>977.497899, 1029.491507</point></points><coordinate>pixel</coordinate><possibleresult><name>A350</name><probability>0.995414137840271</probability></possibleresult></object><object><centerpoint>542.500000, 870.500000</centerpoint><description>None</description><type>rectangle</type><keypoints><keypoint>562.000000, 841.000000</keypoint><keypoint>523.000000, 842.000000</keypoint><keypoint>507.000000, 872.000000</keypoint><keypoint>554.000000, 893.000000</keypoint></keypoints><points><point>520.498204, 905.995490</point><point>493.498306, 837.995721</point><point>560.498077, 811.995143</point><point>587.497975, 879.994913</point><point>520.498204, 905.995490</point></points><coordinate>pixel</coordinate><possibleresult><name>Boeing787</name><probability>0.9860679507255554</probability></possibleresult></object><object><centerpoint>790.500000, 721.000000</centerpoint><description>None</description><type>rectangle</type><keypoints><keypoint>812.000000, 691.000000</keypoint><keypoint>757.000000, 724.000000</keypoint><keypoint>805.000000, 747.000000</keypoint><keypoint>770.000000, 687.500000</keypoint></keypoints><points><point>774.996690, 771.495042</point><point>732.996875, 708.495306</point><point>790.996632, 659.494940</point><point>832.996446, 722.494677</point><point>774.996690, 771.495042</point></points><coordinate>pixel</coordinate><possibleresult><name>Boeing787</name><probability>0.9854574799537659</probability></possibleresult></object><object><centerpoint>954.500000, 630.500000</centerpoint><description>None</description><type>rectangle</type><keypoints><keypoint>977.000000, 598.000000</keypoint><keypoint>920.000000, 633.000000</keypoint><keypoint>971.000000, 662.000000</keypoint><keypoint>932.000000, 589.000000</keypoint></keypoints><points><point>939.683592, 694.822316</point><point>894.683759, 615.822591</point><point>956.683542, 550.822209</point><point>1001.683375, 629.821934</point><point>939.683592, 694.822316</point></points><coordinate>pixel</coordinate><possibleresult><name>A350</name><probability>0.9835192561149597</probability></possibleresult></object><object><centerpoint>981.500000, 385.500000</centerpoint><description>None</description><type>rectangle</type><keypoints><keypoint>971.000000, 366.000000</keypoint><keypoint>1015.000000, 379.000000</keypoint><keypoint>960.000000, 413.000000</keypoint><keypoint>999.500000, 417.000000</keypoint></keypoints><points><point>976.211366, 440.854357</point><point>942.211519, 383.854598</point><point>998.211281, 347.854198</point><point>1032.211127, 404.853957</point><point>976.211366, 440.854357</point></points><coordinate>pixel</coordinate><possibleresult><name>Boeing787</name><probability>0.9760505557060242</probability></possibleresult></object><object><centerpoint>610.000000, 701.750000</centerpoint><description>None</description><type>rectangle</type><keypoints><keypoint>604.000000, 671.000000</keypoint><keypoint>642.000000, 685.000000</keypoint><keypoint>583.000000, 720.000000</keypoint><keypoint>637.000000, 723.000000</keypoint></keypoints><points><point>597.088149, 753.696878</point><point>567.088268, 686.697120</point><point>634.088024, 653.696575</point><point>664.087905, 720.696333</point><point>597.088149, 753.696878</point></points><coordinate>pixel</coordinate><possibleresult><name>Boeing787</name><probability>0.960397481918335</probability></possibleresult></object><object><centerpoint>692.500000, 775.000000</centerpoint><description>None</description><type>rectangle</type><keypoints><keypoint>712.000000, 747.000000</keypoint><keypoint>661.000000, 778.000000</keypoint><keypoint>707.000000, 799.000000</keypoint><keypoint>675.000000, 739.000000</keypoint></keypoints><points><point>672.210616, 811.915047</point><point>638.210770, 744.915330</point><point>708.210472, 718.914744</point><point>742.210319, 785.914461</point><point>672.210616, 811.915047</point></points><coordinate>pixel</coordinate><possibleresult><name>ARJ21</name><probability>0.6209147572517395</probability></possibleresult></object><object><centerpoint>872.500000, 676.500000</centerpoint><description>None</description><type>rectangle</type><keypoints><keypoint>895.000000, 648.000000</keypoint><keypoint>840.000000, 680.000000</keypoint><keypoint>887.000000, 708.000000</keypoint><keypoint>851.000000, 636.000000</keypoint></keypoints><points><point>856.168427, 739.328442</point><point>816.168568, 661.328698</point><point>877.168366, 599.328304</point><point>917.168225, 677.328048</point><point>856.168427, 739.328442</point></points><coordinate>pixel</coordinate><possibleresult><name>Boeing787</name><probability>0.599891185760498</probability></possibleresult></object></objects><research><author>UFMS</author><provider>UFMS</provider><pluginclass>Detection</pluginclass><pluginname>Airplane Detection and Recognition</pluginname><version>4.0</version><time>2020-07-2020-11</time></research></annotation>