<?xml version="1.0" encoding="UTF-8" ?><annotation><source><origin>GF2/GF3</origin><filename>276.tif</filename></source><objects><object><centerpoint>314.000000, 628.500000</centerpoint><description>None</description><type>rectangle</type><keypoints><keypoint>295.000000, 603.000000</keypoint><keypoint>335.000000, 611.000000</keypoint><keypoint>291.000000, 632.000000</keypoint><keypoint>328.000000, 652.000000</keypoint></keypoints><points><point>302.998685, 669.997953</point><point>270.998830, 619.998164</point><point>318.998626, 583.997845</point><point>350.998480, 633.997633</point><point>302.998685, 669.997953</point></points><coordinate>pixel</coordinate><possibleresult><name>A330</name><probability>0.9997562766075134</probability></possibleresult></object><object><centerpoint>144.000000, 709.750000</centerpoint><description>None</description><type>rectangle</type><keypoints><keypoint>116.000000, 695.000000</keypoint><keypoint>172.000000, 709.000000</keypoint><keypoint>139.000000, 729.000000</keypoint><keypoint>152.000000, 677.000000</keypoint></keypoints><points><point>109.479456, 724.094797</point><point>122.479492, 664.094675</point><point>182.479617, 676.094098</point><point>169.479581, 736.094220</point><point>109.479456, 724.094797</point></points><coordinate>pixel</coordinate><possibleresult><name>Boeing777</name><probability>0.9853160977363586</probability></possibleresult></object><object><centerpoint>554.500000, 836.000000</centerpoint><description>None</description><type>rectangle</type><keypoints><keypoint>575.000000, 817.000000</keypoint><keypoint>531.000000, 829.000000</keypoint><keypoint>550.000000, 859.000000</keypoint><keypoint>583.500000, 851.000000</keypoint></keypoints><points><point>513.385431, 854.666936</point><point>548.385623, 803.666671</point><point>604.385919, 828.666239</point><point>569.385728, 879.666504</point><point>513.385431, 854.666936</point></points><coordinate>pixel</coordinate><possibleresult><name>A330</name><probability>0.9737476110458374</probability></possibleresult></object><object><centerpoint>133.500000, 38.500000</centerpoint><description>None</description><type>rectangle</type><keypoints><keypoint>128.000000, 11.000000</keypoint><keypoint>170.000000, 29.000000</keypoint><keypoint>108.000000, 50.000000</keypoint><keypoint>155.000000, 57.000000</keypoint></keypoints><points><point>122.215964, 78.922144</point><point>93.216094, 19.922388</point><point>155.215836, -2.078137</point><point>184.215706, 56.921619</point><point>122.215964, 78.922144</point></points><coordinate>pixel</coordinate><possibleresult><name>A330</name><probability>0.9521973133087158</probability></possibleresult></object><object><centerpoint>470.000000, 881.500000</centerpoint><description>None</description><type>rectangle</type><keypoints><keypoint>459.000000, 864.000000</keypoint><keypoint>495.000000, 877.000000</keypoint><keypoint>450.000000, 899.000000</keypoint><keypoint>493.000000, 906.000000</keypoint></keypoints><points><point>466.497493, 920.996512</point><point>433.497678, 874.996756</point><point>484.497407, 850.996378</point><point>517.497222, 896.996135</point><point>466.497493, 920.996512</point></points><coordinate>pixel</coordinate><possibleresult><name>Boeing777</name><probability>0.9395826458930969</probability></possibleresult></object><object><centerpoint>191.750000, 207.000000</centerpoint><description>None</description><type>rectangle</type><keypoints><keypoint>219.000000, 187.000000</keypoint><keypoint>173.000000, 197.000000</keypoint><keypoint>189.000000, 230.000000</keypoint><keypoint>225.500000, 221.500000</keypoint></keypoints><points><point>152.500913, 219.998926</point><point>193.501166, 171.998640</point><point>250.501512, 199.998235</point><point>209.501259, 247.998521</point><point>152.500913, 219.998926</point></points><coordinate>pixel</coordinate><possibleresult><name>Boeing777</name><probability>0.8872891068458557</probability></possibleresult></object><object><centerpoint>503.500000, 680.500000</centerpoint><description>None</description><type>rectangle</type><keypoints><keypoint>498.000000, 654.000000</keypoint><keypoint>533.000000, 665.000000</keypoint><keypoint>484.000000, 689.000000</keypoint><keypoint>523.000000, 697.000000</keypoint></keypoints><points><point>496.673611, 711.909997</point><point>470.673732, 664.910198</point><point>519.673520, 640.909816</point><point>545.673399, 687.909615</point><point>496.673611, 711.909997</point></points><coordinate>pixel</coordinate><possibleresult><name>Boeing777</name><probability>0.8817793726921082</probability></possibleresult></object><object><centerpoint>540.250000, 740.000000</centerpoint><description>None</description><type>rectangle</type><keypoints><keypoint>534.000000, 714.000000</keypoint><keypoint>570.000000, 725.000000</keypoint><keypoint>518.000000, 751.000000</keypoint><keypoint>556.000000, 757.000000</keypoint></keypoints><points><point>526.297799, 777.845835</point><point>509.297853, 722.845978</point><point>561.297715, 696.845532</point><point>578.297661, 751.845389</point><point>526.297799, 777.845835</point></points><coordinate>pixel</coordinate><possibleresult><name>Boeing777</name><probability>0.8652055263519287</probability></possibleresult></object><object><centerpoint>164.000000, 98.500000</centerpoint><description>None</description><type>rectangle</type><keypoints><keypoint>160.000000, 84.000000</keypoint><keypoint>198.000000, 88.000000</keypoint><keypoint>144.000000, 109.000000</keypoint><keypoint>183.000000, 119.000000</keypoint></keypoints><points><point>162.367360, 131.835103</point><point>125.367587, 85.835372</point><point>179.367270, 61.834978</point><point>216.367043, 107.834708</point><point>162.367360, 131.835103</point></points><coordinate>pixel</coordinate><possibleresult><name>other</name><probability>0.7756314277648926</probability></possibleresult></object><object><centerpoint>293.750000, 963.750000</centerpoint><description>None</description><type>rectangle</type><keypoints><keypoint>317.000000, 943.000000</keypoint><keypoint>275.000000, 956.000000</keypoint><keypoint>335.000000, 973.000000</keypoint><keypoint>293.000000, 989.000000</keypoint></keypoints><points><point>256.001538, 981.497929</point><point>294.001775, 930.497624</point><point>354.002139, 949.497136</point><point>316.001902, 1000.497441</point><point>256.001538, 981.497929</point></points><coordinate>pixel</coordinate><possibleresult><name>Boeing777</name><probability>0.7345873117446899</probability></possibleresult></object></objects><research><author>UFMS</author><provider>UFMS</provider><pluginclass>Detection</pluginclass><pluginname>Airplane Detection and Recognition</pluginname><version>4.0</version><time>2020-07-2020-11</time></research></annotation>