<?xml version="1.0" encoding="UTF-8" ?><annotation><source><origin>GF2/GF3</origin><filename>387.tif</filename></source><objects><object><centerpoint>677.750000, 971.750000</centerpoint><description>None</description><type>rectangle</type><keypoints><keypoint>620.000000, 950.000000</keypoint><keypoint>696.000000, 951.000000</keypoint><keypoint>689.000000, 1002.000000</keypoint><keypoint>625.000000, 1011.000000</keypoint></keypoints><points><point>656.181983, 1040.737110</point><point>581.182459, 978.737495</point><point>658.181980, 919.737099</point><point>733.181504, 981.736714</point><point>656.181983, 1040.737110</point></points><coordinate>pixel</coordinate><possibleresult><name>A350</name><probability>0.9724603295326233</probability></possibleresult></object><object><centerpoint>946.500000, 509.000000</centerpoint><description>None</description><type>rectangle</type><keypoints><keypoint>931.000000, 495.000000</keypoint><keypoint>969.000000, 500.000000</keypoint><keypoint>935.000000, 527.000000</keypoint><keypoint>967.000000, 530.500000</keypoint></keypoints><points><point>945.994262, 550.993980</point><point>905.994510, 508.994231</point><point>955.994211, 478.993916</point><point>995.993962, 520.993666</point><point>945.994262, 550.993980</point></points><coordinate>pixel</coordinate><possibleresult><name>A330</name><probability>0.8541854023933411</probability></possibleresult></object><object><centerpoint>826.000000, 612.500000</centerpoint><description>None</description><type>rectangle</type><keypoints><keypoint>789.000000, 578.000000</keypoint><keypoint>874.000000, 595.000000</keypoint><keypoint>872.000000, 650.000000</keypoint><keypoint>799.000000, 654.000000</keypoint></keypoints><points><point>748.004122, 617.496024</point><point>830.004580, 538.495592</point><point>916.005060, 611.495130</point><point>834.004602, 690.495562</point><point>748.004122, 617.496024</point></points><coordinate>pixel</coordinate><possibleresult><name>Boeing787</name><probability>0.8068091869354248</probability></possibleresult></object></objects><research><author>UFMS</author><provider>UFMS</provider><pluginclass>Detection</pluginclass><pluginname>Airplane Detection and Recognition</pluginname><version>4.0</version><time>2020-07-2020-11</time></research></annotation>