<?xml version="1.0" encoding="UTF-8" ?><annotation><source><origin>GF2/GF3</origin><filename>390.tif</filename></source><objects><object><centerpoint>387.750000, 1007.250000</centerpoint><description>None</description><type>rectangle</type><keypoints><keypoint>367.000000, 986.000000</keypoint><keypoint>415.000000, 996.000000</keypoint><keypoint>377.000000, 1019.000000</keypoint><keypoint>404.000000, 1019.000000</keypoint></keypoints><points><point>380.497061, 1034.497209</point><point>339.497384, 995.497507</point><point>394.496963, 976.497106</point><point>435.496639, 1015.496808</point><point>380.497061, 1034.497209</point></points><coordinate>pixel</coordinate><possibleresult><name>Boeing737</name><probability>0.7656387090682983</probability></possibleresult></object><object><description>None</description><type>rectangle</type><keypoints><keypoint>498.000000, 814.000000</keypoint><keypoint>559.000000, 833.000000</keypoint></keypoints><points><point>523.985415, 837.492710</point><point>465.987042, 808.493519</point><point>529.985258, 817.492626</point><point>587.983630, 846.491817</point><point>523.985415, 837.492710</point></points><coordinate>pixel</coordinate><possibleresult><name>Boeing737</name><probability>0.7461484670639038</probability></possibleresult></object><object><centerpoint>111.250000, 95.750000</centerpoint><description>None</description><type>rectangle</type><keypoints><keypoint>133.000000, 67.000000</keypoint><keypoint>74.000000, 112.000000</keypoint><keypoint>135.000000, 128.000000</keypoint><keypoint>74.500000, 62.500000</keypoint></keypoints><points><point>94.183380, 153.194499</point><point>28.183780, 83.194913</point><point>109.183301, 33.194405</point><point>175.182901, 103.193991</point><point>94.183380, 153.194499</point></points><coordinate>pixel</coordinate><possibleresult><name>Boeing747</name><probability>0.7011080980300903</probability></possibleresult></object><object><centerpoint>915.500000, 540.000000</centerpoint><description>None</description><type>rectangle</type><keypoints><keypoint>899.000000, 528.000000</keypoint><keypoint>939.000000, 529.000000</keypoint><keypoint>899.000000, 561.000000</keypoint><keypoint>940.000000, 561.000000</keypoint></keypoints><points><point>917.994467, 579.495163</point><point>877.994713, 544.495370</point><point>919.994465, 511.495153</point><point>959.994219, 546.494946</point><point>917.994467, 579.495163</point></points><coordinate>pixel</coordinate><possibleresult><name>A330</name><probability>0.6163920164108276</probability></possibleresult></object><object><centerpoint>491.500000, 922.666667</centerpoint><description>None</description><type>rectangle</type><keypoints><keypoint>476.000000, 906.000000</keypoint><keypoint>519.000000, 912.000000</keypoint><keypoint>475.000000, 946.000000</keypoint><keypoint>509.000000, 949.000000</keypoint></keypoints><points><point>486.997677, 973.496845</point><point>450.997855, 924.497074</point><point>500.997621, 887.496755</point><point>536.997443, 936.496526</point><point>486.997677, 973.496845</point></points><coordinate>pixel</coordinate><possibleresult><name>A330</name><probability>0.581122100353241</probability></possibleresult></object></objects><research><author>UFMS</author><provider>UFMS</provider><pluginclass>Detection</pluginclass><pluginname>Airplane Detection and Recognition</pluginname><version>4.0</version><time>2020-07-2020-11</time></research></annotation>