<?xml version="1.0" encoding="UTF-8" ?><annotation><source><origin>GF2/GF3</origin><filename>769.tif</filename></source><objects><object><centerpoint>521.000000, 272.500000</centerpoint><description>None</description><type>rectangle</type><keypoints><keypoint>512.000000, 240.000000</keypoint><keypoint>561.000000, 280.000000</keypoint><keypoint>491.000000, 295.000000</keypoint><keypoint>531.500000, 317.000000</keypoint></keypoints><points><point>488.388466, 327.506925</point><point>469.388518, 243.507110</point><point>554.388330, 234.506280</point><point>573.388279, 318.506096</point><point>488.388466, 327.506925</point></points><coordinate>pixel</coordinate><possibleresult><name>A350</name><probability>0.9952914714813232</probability></possibleresult></object><object><centerpoint>945.500000, 897.500000</centerpoint><description>None</description><type>rectangle</type><keypoints><keypoint>962.000000, 879.000000</keypoint><keypoint>931.000000, 884.000000</keypoint><keypoint>962.000000, 901.000000</keypoint><keypoint>937.000000, 912.000000</keypoint></keypoints><points><point>919.004527, 899.993580</point><point>943.004652, 865.993416</point><point>979.004833, 887.993160</point><point>955.004708, 921.993324</point><point>919.004527, 899.993580</point></points><coordinate>pixel</coordinate><possibleresult><name>Boeing777</name><probability>0.9913592338562012</probability></possibleresult></object><object><centerpoint>981.000000, 18.500000</centerpoint><description>None</description><type>rectangle</type><keypoints><keypoint>996.000000, 3.000000</keypoint><keypoint>973.000000, 6.000000</keypoint><keypoint>995.000000, 25.000000</keypoint><keypoint>965.000000, 33.000000</keypoint></keypoints><points><point>945.328117, 22.671877</point><point>976.328324, -8.328319</point><point>1014.328572, 12.671433</point><point>983.328366, 43.671629</point><point>945.328117, 22.671877</point></points><coordinate>pixel</coordinate><possibleresult><name>Boeing777</name><probability>0.9774060845375061</probability></possibleresult></object><object><centerpoint>243.500000, 685.500000</centerpoint><description>None</description><type>rectangle</type><keypoints><keypoint>249.000000, 668.000000</keypoint><keypoint>219.000000, 677.000000</keypoint><keypoint>256.000000, 694.000000</keypoint><keypoint>229.000000, 708.000000</keypoint></keypoints><points><point>207.418276, 698.163438</point><point>228.418365, 656.163279</point><point>268.418523, 679.162964</point><point>247.418434, 721.163122</point><point>207.418276, 698.163438</point></points><coordinate>pixel</coordinate><possibleresult><name>Boeing777</name><probability>0.9653811454772949</probability></possibleresult></object><object><centerpoint>433.500000, 348.500000</centerpoint><description>None</description><type>rectangle</type><keypoints><keypoint>459.000000, 326.000000</keypoint><keypoint>407.000000, 335.000000</keypoint><keypoint>473.000000, 360.000000</keypoint><keypoint>430.000000, 377.000000</keypoint></keypoints><points><point>390.790026, 365.913377</point><point>422.790169, 302.913114</point><point>488.790450, 328.912560</point><point>456.790307, 391.912824</point><point>390.790026, 365.913377</point></points><coordinate>pixel</coordinate><possibleresult><name>Boeing787</name><probability>0.9458039999008179</probability></possibleresult></object><object><centerpoint>787.500000, 708.000000</centerpoint><description>None</description><type>rectangle</type><keypoints><keypoint>802.000000, 694.000000</keypoint><keypoint>776.000000, 703.000000</keypoint><keypoint>784.000000, 722.000000</keypoint><keypoint>806.000000, 718.000000</keypoint></keypoints><points><point>767.918399, 721.183591</point><point>783.918466, 685.183462</point><point>818.918597, 701.183167</point><point>802.918530, 737.183296</point><point>767.918399, 721.183591</point></points><coordinate>pixel</coordinate><possibleresult><name>Boeing737</name><probability>0.9019436240196228</probability></possibleresult></object><object><centerpoint>985.500000, 187.000000</centerpoint><description>None</description><type>rectangle</type><keypoints><keypoint>998.000000, 165.000000</keypoint><keypoint>960.000000, 182.000000</keypoint><keypoint>1002.000000, 205.000000</keypoint><keypoint>967.000000, 213.000000</keypoint></keypoints><points><point>942.642618, 198.083715</point><point>972.642757, 149.083506</point><point>1021.642974, 181.083151</point><point>991.642835, 230.083361</point><point>942.642618, 198.083715</point></points><coordinate>pixel</coordinate><possibleresult><name>Boeing737</name><probability>0.8948571085929871</probability></possibleresult></object><object><centerpoint>393.000000, 429.500000</centerpoint><description>None</description><type>rectangle</type><keypoints><keypoint>422.000000, 405.000000</keypoint><keypoint>365.000000, 415.000000</keypoint><keypoint>437.000000, 445.000000</keypoint><keypoint>391.000000, 460.000000</keypoint></keypoints><points><point>342.119453, 447.049671</point><point>387.119699, 382.049331</point><point>459.120083, 414.048777</point><point>414.119837, 479.049117</point><point>342.119453, 447.049671</point></points><coordinate>pixel</coordinate><possibleresult><name>A350</name><probability>0.8131598830223083</probability></possibleresult></object><object><centerpoint>677.000000, 295.500000</centerpoint><description>None</description><type>rectangle</type><keypoints><keypoint>688.000000, 281.000000</keypoint><keypoint>659.000000, 287.000000</keypoint><keypoint>687.000000, 308.000000</keypoint><keypoint>665.000000, 316.000000</keypoint></keypoints><points><point>646.003075, 304.495508</point><point>670.003197, 269.495345</point><point>706.003371, 292.495091</point><point>682.003250, 327.495253</point><point>646.003075, 304.495508</point></points><coordinate>pixel</coordinate><possibleresult><name>Boeing737</name><probability>0.7513512969017029</probability></possibleresult></object><object><centerpoint>355.000000, 509.000000</centerpoint><description>None</description><type>rectangle</type><keypoints><keypoint>378.000000, 487.000000</keypoint><keypoint>326.000000, 496.000000</keypoint><keypoint>353.000000, 536.000000</keypoint><keypoint>390.500000, 528.500000</keypoint></keypoints><points><point>299.501811, 525.497979</point><point>352.502139, 466.497625</point><point>421.502560, 503.497155</point><point>368.502232, 562.497509</point><point>299.501811, 525.497979</point></points><coordinate>pixel</coordinate><possibleresult><name>Boeing787</name><probability>0.7207661867141724</probability></possibleresult></object><object><centerpoint>156.000000, 602.000000</centerpoint><description>None</description><type>rectangle</type><keypoints><keypoint>160.000000, 581.000000</keypoint><keypoint>135.000000, 595.000000</keypoint><keypoint>175.000000, 609.000000</keypoint><keypoint>145.000000, 617.000000</keypoint></keypoints><points><point>127.000321, 616.498831</point><point>139.000361, 573.498723</point><point>181.000470, 586.498334</point><point>169.000430, 629.498442</point><point>127.000321, 616.498831</point></points><coordinate>pixel</coordinate><possibleresult><name>Boeing777</name><probability>0.6819296479225159</probability></possibleresult></object><object><centerpoint>18.500000, 366.500000</centerpoint><description>None</description><type>rectangle</type><keypoints><keypoint>30.000000, 339.000000</keypoint><keypoint>9.000000, 368.000000</keypoint><keypoint>63.000000, 369.000000</keypoint><keypoint>36.000000, 402.000000</keypoint></keypoints><points><point>4.444435, 400.999956</point><point>-2.555548, 338.000026</point><point>60.444382, 337.999396</point><point>67.444365, 400.999326</point><point>4.444435, 400.999956</point></points><coordinate>pixel</coordinate><possibleresult><name>Boeing747</name><probability>0.6711900234222412</probability></possibleresult></object><object><centerpoint>308.000000, 596.500000</centerpoint><description>None</description><type>rectangle</type><keypoints><keypoint>343.000000, 574.000000</keypoint><keypoint>277.000000, 580.000000</keypoint><keypoint>347.000000, 617.000000</keypoint><keypoint>309.000000, 635.000000</keypoint></keypoints><points><point>247.080285, 611.914357</point><point>307.080627, 547.914003</point><point>378.081029, 598.913574</point><point>318.080687, 662.913929</point><point>247.080285, 611.914357</point></points><coordinate>pixel</coordinate><possibleresult><name>A350</name><probability>0.6007736325263977</probability></possibleresult></object></objects><research><author>UFMS</author><provider>UFMS</provider><pluginclass>Detection</pluginclass><pluginname>Airplane Detection and Recognition</pluginname><version>4.0</version><time>2020-07-2020-11</time></research></annotation>