<?xml version="1.0" encoding="UTF-8" ?><annotation><source><origin>GF2/GF3</origin><filename>889.tif</filename></source><objects><object><centerpoint>46.000000, 815.500000</centerpoint><description>None</description><type>rectangle</type><keypoints><keypoint>70.000000, 793.000000</keypoint><keypoint>11.000000, 801.000000</keypoint><keypoint>59.000000, 848.000000</keypoint><keypoint>16.500000, 843.500000</keypoint></keypoints><points><point>-18.765486, 822.269524</point><point>39.234833, 765.269221</point><point>100.235167, 818.268893</point><point>42.234848, 875.269196</point><point>-18.765486, 822.269524</point></points><coordinate>pixel</coordinate><possibleresult><name>Boeing787</name><probability>0.9359752535820007</probability></possibleresult></object></objects><research><author>UFMS</author><provider>UFMS</provider><pluginclass>Detection</pluginclass><pluginname>Airplane Detection and Recognition</pluginname><version>4.0</version><time>2020-07-2020-11</time></research></annotation>