<?xml version="1.0" encoding="UTF-8" ?><annotation><source><origin>GF2/GF3</origin><filename>907.tif</filename></source><objects><object><centerpoint>947.666667, 593.333333</centerpoint><description>None</description><type>rectangle</type><keypoints><keypoint>976.000000, 608.000000</keypoint><keypoint>920.000000, 613.000000</keypoint><keypoint>954.000000, 651.000000</keypoint><keypoint>945.000000, 588.000000</keypoint></keypoints><points><point>917.065687, 649.472981</point><point>907.065711, 577.473082</point><point>980.065609, 580.472347</point><point>990.065585, 652.472246</point><point>917.065687, 649.472981</point></points><coordinate>pixel</coordinate><possibleresult><name>Boeing737</name><probability>0.9988707900047302</probability></possibleresult></object><object><centerpoint>625.000000, 761.000000</centerpoint><description>None</description><type>rectangle</type><keypoints><keypoint>638.000000, 756.000000</keypoint><keypoint>614.000000, 767.000000</keypoint><keypoint>631.000000, 773.000000</keypoint></keypoints><points><point>618.264683, 778.372502</point><point>609.264721, 754.372575</point><point>633.264645, 743.372374</point><point>642.264608, 767.372301</point><point>618.264683, 778.372502</point></points><coordinate>pixel</coordinate><possibleresult><name>Boeing737</name><probability>0.9983094930648804</probability></possibleresult></object><object><centerpoint>773.000000, 643.000000</centerpoint><description>None</description><type>rectangle</type><keypoints><keypoint>805.000000, 621.000000</keypoint><keypoint>735.000000, 629.000000</keypoint><keypoint>776.000000, 674.000000</keypoint><keypoint>762.500000, 598.500000</keypoint></keypoints><points><point>735.498392, 684.993080</point><point>716.498443, 602.993257</point><point>797.498267, 580.992497</point><point>816.498216, 662.992321</point><point>735.498392, 684.993080</point></points><coordinate>pixel</coordinate><possibleresult><name>Boeing747</name><probability>0.9960796236991882</probability></possibleresult></object><object><centerpoint>873.000000, 189.000000</centerpoint><description>None</description><type>rectangle</type><keypoints><keypoint>877.000000, 175.000000</keypoint><keypoint>890.000000, 187.000000</keypoint><keypoint>860.000000, 191.000000</keypoint><keypoint>875.000000, 197.000000</keypoint></keypoints><points><point>856.501497, 204.491290</point><point>861.501516, 175.491238</point><point>892.501570, 172.490924</point><point>887.501551, 201.490975</point><point>856.501497, 204.491290</point></points><coordinate>pixel</coordinate><possibleresult><name>Boeing737</name><probability>0.9790058732032776</probability></possibleresult></object></objects><research><author>UFMS</author><provider>UFMS</provider><pluginclass>Detection</pluginclass><pluginname>Airplane Detection and Recognition</pluginname><version>4.0</version><time>2020-07-2020-11</time></research></annotation>